claude_sdk/__init__.py
claude_sdk/errors.py
claude_sdk/executor.py
claude_sdk/message.py
claude_sdk/models.py
claude_sdk/parser.py
claude_sdk/py.typed
claude_sdk/session.py
claude_sdk/utils.py
claude_sdk-1.0.0.dist-info/METADATA
claude_sdk-1.0.0.dist-info/WHEEL
claude_sdk-1.0.0.dist-info/licenses/LICENSE
claude_sdk-1.0.0.dist-info/RECORD
