Metadata-Version: 2.4
Name: claude-sdk
Version: 1.0.0
Summary: Typed Python SDK for parsing and analyzing Claude Code sessions
Project-URL: Homepage, https://github.com/darinkishore/claude-sdk
Project-URL: Repository, https://github.com/darinkishore/claude-sdk
Project-URL: Issues, https://github.com/darinkishore/claude-sdk/issues
Author-email: Darin Kishore <darinkishore@protonmail.com>
License-File: LICENSE
Classifier: Development Status :: 5 - Production/Stable
Classifier: Intended Audience :: Developers
Classifier: License :: OSI Approved :: MIT License
Classifier: Programming Language :: Python :: 3
Classifier: Programming Language :: Python :: 3.11
Classifier: Programming Language :: Python :: 3.12
Classifier: Topic :: Software Development :: Libraries :: Python Modules
Classifier: Topic :: Utilities
Classifier: Typing :: Typed
Requires-Python: >=3.11
Requires-Dist: pydantic<3.0,>=2.11.5
Provides-Extra: all
Requires-Dist: basedpyright>=1.19.0; extra == 'all'
Requires-Dist: gitpython>=3.1.0; extra == 'all'
Requires-Dist: hypothesis>=6.0.0; extra == 'all'
Requires-Dist: pre-commit>=3.0.0; extra == 'all'
Requires-Dist: pytest-cov>=4.0.0; extra == 'all'
Requires-Dist: pytest>=7.0.0; extra == 'all'
Requires-Dist: ruff>=0.1.0; extra == 'all'
Requires-Dist: types-python-dateutil; extra == 'all'
Provides-Extra: dev
Requires-Dist: basedpyright>=1.19.0; extra == 'dev'
Requires-Dist: hypothesis>=6.0.0; extra == 'dev'
Requires-Dist: pre-commit>=3.0.0; extra == 'dev'
Requires-Dist: pytest-cov>=4.0.0; extra == 'dev'
Requires-Dist: pytest>=7.0.0; extra == 'dev'
Requires-Dist: ruff>=0.1.0; extra == 'dev'
Requires-Dist: types-python-dateutil; extra == 'dev'
Provides-Extra: git
Requires-Dist: gitpython>=3.1.0; extra == 'git'
